DEPENDS
MANIFEST.in
README
apache-comsat.conf
orbited-0.conf
orbited-1.conf
orbited.conf
setup.py
stomp.py
comsat/__init__.py
comsat/manage.py
comsat/runscript.py
comsat/secrets.py.template
comsat/settings.py
comsat/urls.py
comsat/balancer/__init__.py
comsat/balancer/models.py
comsat/balancer/tests.py
comsat/balancer/urls.py
comsat/balancer/views.py
comsat/conf/apache.conf
comsat/third_party/lib/manicscript/__init__.py
comsat/third_party/lib/manicscript/jstime.py
comsat/third_party/lib/manicscript/crypto/__init__.py
comsat/third_party/lib/manicscript/crypto/aes.py
comsat/third_party/lib/manicscript/crypto/secrand.py
comsat/third_party/lib/manicscript/crypto/sign.py
comsat/third_party/lib/manicscript/djchat/__init__.py
comsat/third_party/lib/manicscript/djchat/client.py
comsat/third_party/lib/manicscript/djchat/sessions.py
comsat/third_party/lib/manicscript/jsoncore/__init__.py
comsat/third_party/lib/manicscript/jsoncore/comsat.py
comsat/third_party/lib/manicscript/jsoncore/decorators.py
comsat/third_party/lib/manicscript/jsoncore/json.py
comsat/third_party/lib/manicscript/jsoncore/models.py
comsat/third_party/lib/manicscript/jsoncore/urls.py
comsat/third_party/lib/manicscript/jsoncore/views.py
comsat/third_party/lib/manicscript/kerby/__init__.py
comsat/third_party/lib/manicscript/kerby/assertions.py
comsat/third_party/lib/manicscript/kerby/cipher.py
comsat/third_party/lib/manicscript/kerby/ticket.py
comsat/third_party/lib/manicscript/replay/__init__.py
comsat/third_party/lib/manicscript/replay/client.py
comsat/third_party/lib/manicscript/replay/instant_replay.py
comsat/third_party/lib/manicscript/twisted/__init__.py
comsat/third_party/lib/manicscript/twisted/runscript.py
comsat/third_party/lib/manicscript/twisted/stomp.py
manicscript/__init__.py
manicscript/jstime.py
manicscript.egg-info/PKG-INFO
manicscript.egg-info/SOURCES.txt
manicscript.egg-info/dependency_links.txt
manicscript.egg-info/requires.txt
manicscript.egg-info/top_level.txt
manicscript/crypto/__init__.py
manicscript/crypto/aes.py
manicscript/crypto/secrand.py
manicscript/crypto/sign.py
manicscript/djchat/__init__.py
manicscript/djchat/client.py
