Metadata-Version: 1.0
Name: manicscript
Version: 0.1.2
Summary: Python and JavaScript libraries for event-driven interactive web applications
Home-page: http://pypi.python.org/pypi/manicscript/
Author: Jason Alonso
Author-email: jalonso@media.mit.edu
License: UNKNOWN
Platform: UNKNOWN
